[{"persona":{"nombre":"Luisa","apellido":"Duque","id":"456","pais":"Colombia"},"contrato":{"prima":0.0,"cesantias":0.0,"fechaInicio":{"year":2022,"month":2,"day":20},"arl":{"nombre":"SB","tipoAfiliacion":"Tipo B"},"salario":3000.0},"eps":{"nombre":"Sura","tipoAfiliacion":"beneficiario"},"estado":"activo","cargo":"Analista"}][{"persona":{"nombre":"Jhonatan","apellido":"Tamayo","id":"123","pais":"Colombia"},"contrato":{"prima":0.0,"cesantias":0.0,"fechaInicio":{"year":2022,"month":2,"day":20},"arl":{"nombre":"JhonARL","tipoAfiliacion":"Tipo C"},"salario":2000.0},"eps":{"nombre":"Sura","tipoAfiliacion":"beneficiario"},"estado":"activo","cargo":"Tester"}]